bedboss/__init__.py
bedboss/__main__.py
bedboss/_version.py
bedboss/bedboss.py
bedboss/cli.py
bedboss/const.py
bedboss/exceptions.py
bedboss/models.py
bedboss/skipper.py
bedboss/utils.py
bedboss/bbuploader/__init__.py
bedboss/bbuploader/cli.py
bedboss/bbuploader/constants.py
bedboss/bbuploader/main.py
bedboss/bbuploader/metadata_extractor.py
bedboss/bbuploader/models.py
bedboss/bbuploader/utils.py
bedboss/bedbuncher/__init__.py
bedboss/bedbuncher/bedbuncher.py
bedboss/bedbuncher/tools/bedsetStat.R
bedboss/bedclassifier/__init__.py
bedboss/bedclassifier/bedclassifier.py
bedboss/bedmaker/__init__.py
bedboss/bedmaker/bedmaker.py
bedboss/bedmaker/const.py
bedboss/bedmaker/models.py
bedboss/bedmaker/utils.py
bedboss/bedstat/__init__.py
bedboss/bedstat/bedstat.py
bedboss/bedstat/gc_content.py
bedboss/bedstat/r_service.py
bedboss/bedstat/tools/r-service.R
bedboss/bedstat/tools/regionstat.R
bedboss/bedstat/tools/regionstat_cli.R
bedboss/qdrant_index/__init__.py
bedboss/qdrant_index/qdrant_index.py
bedboss/refgenome_validator/README.md
bedboss/refgenome_validator/__init__.py
bedboss/refgenome_validator/const.py
bedboss/refgenome_validator/genome_model.py
bedboss/refgenome_validator/main.py
bedboss/refgenome_validator/models.py
bedboss/refgenome_validator/refgenie_chrom_sizes.py
bedboss/refgenome_validator/utils.py
bedboss/refgenome_validator/chrom_sizes/ensembl_hg38.chrom.sizes
bedboss/refgenome_validator/chrom_sizes/ncbi_hg38.chrom.sizes
bedboss/refgenome_validator/chrom_sizes/ucsc_dm6.chrom.sizes
bedboss/refgenome_validator/chrom_sizes/ucsc_hg19.chrom.sizes
bedboss/refgenome_validator/chrom_sizes/ucsc_hg38.chrom.sizes
bedboss/refgenome_validator/chrom_sizes/ucsc_mm10.chrom.sizes
bedboss/refgenome_validator/chrom_sizes/ucsc_mm39.chrom.sizes
bedboss/refgenome_validator/chrom_sizes/ucsc_mm9.chrom.sizes
bedboss/refgenome_validator/chrom_sizes/ucsc_panTo6.chrom.sizes
bedboss/refgenome_validator/chrom_sizes/ucsc_sacCer3.chrom.sizes
bedboss/scripts/__init__.py
bedboss-0.9.2.dist-info/licenses/LICENSE
bedboss-0.9.2.dist-info/METADATA
bedboss-0.9.2.dist-info/WHEEL
bedboss-0.9.2.dist-info/entry_points.txt
bedboss-0.9.2.dist-info/top_level.txt
bedboss-0.9.2.dist-info/RECORD
