Metadata-Version: 2.4
Name: bedboss
Version: 0.9.2
Summary: Pipelines for genomic region file to produce bed files, and it's statistics
Home-page: https://databio.org
Author-email: khorosh@virginia.edu
License: BSD2
Keywords: project,bioinformatics,sequencing,ngs,workflow
Classifier: Development Status :: 3 - Alpha
Classifier: License :: OSI Approved :: BSD License
Classifier: Programming Language :: Python :: 3.10
Classifier: Programming Language :: Python :: 3.11
Classifier: Programming Language :: Python :: 3.12
Classifier: Programming Language :: Python :: 3.13
Classifier: Topic :: Scientific/Engineering :: Bio-Informatics
License-File: LICENSE
Requires-Dist: logmuse>=0.2.7
Requires-Dist: coloredlogs>=15.0.1
Requires-Dist: eido>=0.2.4
Requires-Dist: peppy>=0.40.7
Requires-Dist: yacman>=0.8.4
Requires-Dist: requests>=2.28.2
Requires-Dist: piper>=v0.14.3
Requires-Dist: bbconf>=0.14.3
Requires-Dist: refgenconf>=0.12.2
Requires-Dist: pandas>=2.0.0
Requires-Dist: ubiquerg>=0.6.2
Requires-Dist: bedms>=0.1.0
Requires-Dist: pephubclient>=0.5.0
Dynamic: author-email
Dynamic: classifier
Dynamic: description
Dynamic: description-content-type
Dynamic: home-page
Dynamic: keywords
Dynamic: license
Dynamic: license-file
Dynamic: requires-dist
Dynamic: summary
